./.gitignore
./LICENSE
./PKG-INFO
./README.md
./black_orchid.py
./config.yaml
./language.json
./librarian.py
./package_name
./pyproject.toml
./requirements.txt
./test_pdf_ingestion.py
./working_preferences.md
./modules/code_quality.py
./modules/config_manager.py
./modules/debug_env.py
./modules/librarian_client.py
./modules/project_utils.py
./modules/python_repl.py
./modules/semantic_memory.py
./modules/session_utils.py
./modules/skills_loader.py
./modules/system_utils.py
./modules/skills/black_orchid_audit.md
./modules/skills/documentation_optimizer.md
./modules/skills/documentation_state_reviewer.md
./modules/skills/product_framing.md
./modules/skills/project_estimator.md
./modules/skills/python_code_review.md
./modules/skills/technical_reflection.md
./tests/test_proxy_handler.py
./tests/test_reload.py
./tests/fixtures/broken_module.py
./tests/fixtures/local_docs.py
./tests/fixtures/web_tools.py
iflow_mcp_aj_gonzalez_black_orchid-0.1.0.dist-info/METADATA
iflow_mcp_aj_gonzalez_black_orchid-0.1.0.dist-info/WHEEL
iflow_mcp_aj_gonzalez_black_orchid-0.1.0.dist-info/entry_points.txt
iflow_mcp_aj_gonzalez_black_orchid-0.1.0.dist-info/licenses/LICENSE
iflow_mcp_aj_gonzalez_black_orchid-0.1.0.dist-info/RECORD
