Metadata-Version: 2.4
Name: iflow-mcp_aj-gonzalez_black-orchid
Version: 0.1.0
Summary: Black Orchid: An Extendable Collaborative Environment Framework - Hot-reloadable MCP proxy server
License-File: LICENSE
Requires-Python: >=3.8
Requires-Dist: beautifulsoup4>=4.12
Requires-Dist: chromadb>=0.4.0
Requires-Dist: ebooklib>=0.18
Requires-Dist: fastmcp>=0.1.0
Requires-Dist: lxml>=4.9
Requires-Dist: mobi>=0.3.3
Requires-Dist: pymupdf4llm>=0.0.1
Requires-Dist: python-toon>=0.1.0
Requires-Dist: pyyaml>=6.0
